comtypes/GUID.py
comtypes/__init__.py
comtypes/_comobject.py
comtypes/_meta.py
comtypes/_safearray.py
comtypes/automation.py
comtypes/connectionpoints.py
comtypes/errorinfo.py
comtypes/git.py
comtypes/hresult.py
comtypes/logutil.py
comtypes/messageloop.py
comtypes/npsupport.py
comtypes/patcher.py
comtypes/persist.py
comtypes/safearray.py
comtypes/shelllink.py
comtypes/typeinfo.py
comtypes/util.py
comtypes/viewobject.py
comtypes/client/__init__.py
comtypes/client/_code_cache.py
comtypes/client/_events.py
comtypes/client/_generate.py
comtypes/client/dynamic.py
comtypes/client/lazybind.py
comtypes/server/__init__.py
comtypes/server/automation.py
comtypes/server/connectionpoints.py
comtypes/server/inprocserver.py
comtypes/server/localserver.py
comtypes/server/register.py
comtypes/server/w_getopt.py
comtypes/test/TestComServer.idl
comtypes/test/TestComServer.py
comtypes/test/TestComServer.tlb
comtypes/test/TestDispServer.idl
comtypes/test/TestDispServer.py
comtypes/test/TestDispServer.tlb
comtypes/test/__init__.py
comtypes/test/find_memleak.py
comtypes/test/mylib.idl
comtypes/test/mytypelib.idl
comtypes/test/runtests.py
comtypes/test/setup.py
comtypes/test/test_BSTR.py
comtypes/test/test_DISPPARAMS.py
comtypes/test/test_GUID.py
comtypes/test/test_QueryService.py
comtypes/test/test_agilent.py
comtypes/test/test_avmc.py
comtypes/test/test_basic.py
comtypes/test/test_casesensitivity.py
comtypes/test/test_client.py
comtypes/test/test_collections.py
comtypes/test/test_comserver.py
comtypes/test/test_createwrappers.py
comtypes/test/test_dict.py
comtypes/test/test_dispinterface.py
comtypes/test/test_dyndispatch.py
comtypes/test/test_excel.py
comtypes/test/test_findgendir.py
comtypes/test/test_getactiveobj.py
comtypes/test/test_ie.py
comtypes/test/test_jscript.js
comtypes/test/test_msscript.py
comtypes/test/test_outparam.py
comtypes/test/test_propputref.py
comtypes/test/test_pump_events.py
comtypes/test/test_safearray.py
comtypes/test/test_sapi.py
comtypes/test/test_server.py
comtypes_fork-1.1.10.dist-info/LICENSE.txt
comtypes_fork-1.1.10.dist-info/METADATA
comtypes_fork-1.1.10.dist-info/WHEEL
comtypes_fork-1.1.10.dist-info/top_level.txt
comtypes_fork-1.1.10.dist-info/RECORD
