Metadata-Version: 2.1
Name: comtypes-fork
Version: 1.1.10
Summary: Pure Python COM package
Home-page: https://github.com/enthought/comtypes
Author: Thomas Heller
Author-email: theller@python.net
License: MIT License
Download-URL: https://github.com/enthought/comtypes/releases
Platform: UNKNOWN
Classifier: Development Status :: 5 - Production/Stable
Classifier: Intended Audience :: Developers
Classifier: License :: OSI Approved :: MIT License
Classifier: Operating System :: Microsoft :: Windows
Classifier: Programming Language :: Python
Classifier: Programming Language :: Python :: 2.6
Classifier: Programming Language :: Python :: 2.7
Classifier: Programming Language :: Python :: 3
Classifier: Topic :: Software Development :: Libraries :: Python Modules
License-File: LICENSE.txt
Requires-Dist: setuptools (<=57.5.0)
Requires-Dist: comtypes
